LICENSE
MANIFEST.in
README.md
requirements.txt
setup.py
causal_strength.egg-info/PKG-INFO
causal_strength.egg-info/SOURCES.txt
causal_strength.egg-info/dependency_links.txt
causal_strength.egg-info/entry_points.txt
causal_strength.egg-info/requires.txt
causal_strength.egg-info/top_level.txt
causalstrength/__init__.py
causalstrength/evaluator.py
causalstrength/models/__init__.py
causalstrength/models/ceq.py
causalstrength/models/cesar.py
causalstrength/utils/__init__.py
causalstrength/utils/download_data.py
causalstrength/visualization/__init__.py
causalstrength/visualization/causal_heatmap.py