Metadata-Version: 2.1
Name: causal-strength
Version: 0.1.0
Summary: A package for evaluating causal strength intensity between cause and effect.
Home-page: https://github.com/cui-shaobo/causal-strength
Author: Shaobo Cui
Author-email: shaobo.cui@epfl.ch
License: UNKNOWN
Platform: UNKNOWN
Classifier: Programming Language :: Python :: 3
Classifier: Operating System :: OS Independent
Requires-Python: >=3.7
License-File: LICENSE
